.coveragerc
.git_archival.txt
.gitattributes
.gitignore
.readthedocs.yml
CHANGES.rst
LICENSE.rst
README.md
pyproject.toml
requirements.txt
setup.cfg
setup.py
.github/dependabot.yml
.github/workflows/linting.yaml
.github/workflows/monthly-warning-test.yaml
.github/workflows/test_releases.yaml
.github/workflows/tests_cron.yaml
diffstar/__init__.py
diffstar/_version.py
diffstar/defaults.py
diffstar/mgas_model.py
diffstar/sfh_model.py
diffstar/utils.py
diffstar.egg-info/PKG-INFO
diffstar.egg-info/SOURCES.txt
diffstar.egg-info/dependency_links.txt
diffstar.egg-info/requires.txt
diffstar.egg-info/top_level.txt
diffstar/data_loaders/__init__.py
diffstar/data_loaders/extract_galacticus_sfh_data.py
diffstar/data_loaders/load_galacticus_sfh.py
diffstar/data_loaders/load_smah_data.py
diffstar/data_loaders/utils.py
diffstar/data_loaders/tests/__init__.py
diffstar/data_loaders/tests/test_load_galacticus_sfh.py
diffstar/data_loaders/tests/test_load_smah_data.py
diffstar/data_loaders/tests/test_utils.py
diffstar/data_loaders/tests/testing_data/subvol_000_diffmah_fits.h5
diffstar/diffstarpop/__init__.py
diffstar/diffstarpop/defaults.py
diffstar/diffstarpop/mc_diffstarpop_mgash.py
diffstar/diffstarpop/param_utils.py
diffstar/diffstarpop/utils.py
diffstar/diffstarpop/data/README.txt
diffstar/diffstarpop/data/des_y3_rsmodel_v0.8.1.fits
diffstar/diffstarpop/kernels/__init__.py
diffstar/diffstarpop/kernels/defaults_mgash.py
diffstar/diffstarpop/kernels/diffstarpop_mgash.py
diffstar/diffstarpop/kernels/satquenchpop_model.py
diffstar/diffstarpop/kernels/sfh_pdf_mgash.py
diffstar/diffstarpop/kernels/params/__init__.py
diffstar/diffstarpop/kernels/params/params_diffstarfits_mgash.py
diffstar/diffstarpop/kernels/params/params_diffstarfits_mgash_galacticus_in_plus_ex_situ.py
diffstar/diffstarpop/kernels/params/params_diffstarfits_mgash_galacticus_in_situ.py
diffstar/diffstarpop/kernels/params/params_diffstarfits_mgash_smdpl_dr1.py
diffstar/diffstarpop/kernels/params/params_diffstarfits_mgash_smdpl_dr1_nomerging.py
diffstar/diffstarpop/kernels/params/params_diffstarfits_mgash_tng.py
