Metadata-Version: 2.4
Name: diffstar
Version: 1.0.0
Summary: Differentiable Star Formation Histories
Author-email: Alex Alarcon <alexalarcongonzalez@gmail.com>
License: BSD 3-Clause License
Project-URL: home, https://github.com/ArgonneCPAC/diffstar
Classifier: Programming Language :: Python :: 3
Requires-Python: >=3.11
License-File: LICENSE.rst
Requires-Dist: diffmah>=0.7.1
Requires-Dist: numpy
Requires-Dist: jax
Requires-Dist: h5py
Dynamic: license-file
